BeginnersbookPerlJiaochengChuyiFix1/README.md
BeginnersbookPerlJiaochengChuyiFix1/__init__.py
BeginnersbookPerlJiaochengChuyiFix1/__main__.py
BeginnersbookPerlJiaochengChuyiFix1/file.epub
BeginnersbookPerlJiaochengChuyiFix1/index.html
BeginnersbookPerlJiaochengChuyiFix1/css/__init__.py
BeginnersbookPerlJiaochengChuyiFix1/css/annotations.css
BeginnersbookPerlJiaochengChuyiFix1/css/main.css
BeginnersbookPerlJiaochengChuyiFix1/css/normalize.css
BeginnersbookPerlJiaochengChuyiFix1/css/popup.css
BeginnersbookPerlJiaochengChuyiFix1/font/__init__.py
BeginnersbookPerlJiaochengChuyiFix1/font/fontello.eot
BeginnersbookPerlJiaochengChuyiFix1/font/fontello.svg
BeginnersbookPerlJiaochengChuyiFix1/font/fontello.ttf
BeginnersbookPerlJiaochengChuyiFix1/font/fontello.woff
BeginnersbookPerlJiaochengChuyiFix1/img/__init__.py
BeginnersbookPerlJiaochengChuyiFix1/img/annotator-glyph-sprite.png
BeginnersbookPerlJiaochengChuyiFix1/img/annotator-icon-sprite.png
BeginnersbookPerlJiaochengChuyiFix1/img/apple-touch-icon.png
BeginnersbookPerlJiaochengChuyiFix1/img/cancelfullscreen.png
BeginnersbookPerlJiaochengChuyiFix1/img/close.png
BeginnersbookPerlJiaochengChuyiFix1/img/fullscreen.png
BeginnersbookPerlJiaochengChuyiFix1/img/loader.gif
BeginnersbookPerlJiaochengChuyiFix1/img/menu-icon.png
BeginnersbookPerlJiaochengChuyiFix1/img/save.png
BeginnersbookPerlJiaochengChuyiFix1/img/saved.png
BeginnersbookPerlJiaochengChuyiFix1/img/settings-s.png
BeginnersbookPerlJiaochengChuyiFix1/img/settings.png
BeginnersbookPerlJiaochengChuyiFix1/img/star.png
BeginnersbookPerlJiaochengChuyiFix1/js/__init__.py
BeginnersbookPerlJiaochengChuyiFix1/js/epub.js
BeginnersbookPerlJiaochengChuyiFix1/js/epub.min.js
BeginnersbookPerlJiaochengChuyiFix1/js/epub.min.map
BeginnersbookPerlJiaochengChuyiFix1/js/hooks.min.js
BeginnersbookPerlJiaochengChuyiFix1/js/hooks.min.map
BeginnersbookPerlJiaochengChuyiFix1/js/reader.js
BeginnersbookPerlJiaochengChuyiFix1/js/reader.js.map
BeginnersbookPerlJiaochengChuyiFix1/js/reader.min.js
beginnersbook_perl_jiaocheng_chuyi_fix1-2025.3.24.0.dist-info/METADATA
beginnersbook_perl_jiaocheng_chuyi_fix1-2025.3.24.0.dist-info/WHEEL
beginnersbook_perl_jiaocheng_chuyi_fix1-2025.3.24.0.dist-info/entry_points.txt
beginnersbook_perl_jiaocheng_chuyi_fix1-2025.3.24.0.dist-info/top_level.txt
beginnersbook_perl_jiaocheng_chuyi_fix1-2025.3.24.0.dist-info/RECORD
